{"name":"Perdomo Reserve Limited Cameroon Edition Petit Corona","url":"https://www.noblego.de/perdomo-reserve-limited-cameroon-edition-petit-corona/","brand":"Perdomo","series":"Limited Cameroon Edition","details":{"Fazit":"Mit Limited Editions ist es so eine Sache. Wenn sie ausverkauft sind, sind sie ausverkauft und werden nicht mehr nachproduziert. Sichern Sie sich also schnell eine oder mehrere der eleganten Perdomo Reserve Limited Cameroon Edition Petit Corona und erleben Sie die wunderbar aromatische  Vereinigung der südamerikanischen und  afrikanischen Tropen.","Genuss":"Fast ist sie gar nicht als Perdomo Zigarre zu erkennen, fehlt ihr doch die markentypische strahlende Sonne aus Tabakblättern auf dem Zigarrenring. Und doch handelt es sich bei der Perdomo Reserve Limited Cameroon Edition Petit Corona um eine Zigarre aus dem Hause Perdomo. Unverkennbar ihr Blend aus Tabaken, die aus den fruchtbaren Tälern Estelis, Condegas und Jalapas in Nicaragua stammen und der gekrönt wird von einem tiefbraunen, ölig-glänzenden Deckblatt aus Kamerun. Florale Aromen mit Heu- und Kräuternuancen im Kaltzug. Die ersten Züge nach dem Entzünden sind süßlich mit Gras- und Zitrusnoten, dann treten holzige Töne und Kaffee in den Vordergrund. Im zweiten Drittel bleiben die süßen Fruchtnoten erhalten, die Basis bestimmen aber intensive Kaffee- und Lederaromen. Im Finale scheinen sich die Aromen gegenseitig übertreffen zu wollen. Das Lederaroma wird schwächer, dafür kommen Kaffee und Schokoladenaromen durch, die mit würzigen Gras- und Holztönen konkurrieren. Ein rundum gelungener Aromencocktail, der bei gleichmäßigem Abbrand Rauchgenuss bis zu einer Stunde bietet.","Hintergrund":"Mit Nick Perdomo Jr. ist die Familie Perdomo in dritter Generation in der Tabakbranche vertreten. Schon der Vater und Großvater widmeten sich ihrer Leidenschaft und rollten für namhafte Manufakturen wie H. Upmann oder Partagas in Kuba Zigarren. Nach der Revolution vom kommunistischen Regime verfolgt, begann ein langer Leidensweg der Familie, der mit der Firmengründung 1992 und dem anschließenden Erfolg zum Glück doch noch einen versöhnlichen Abschluss gefunden hat."},"diameter_mm":16,"ring":40,"length_mm":114,"length_inch":0,"format":"Petit Corona","manufactureOrigin":"Nicaragua","construction":"Longfiller","isBoxpressed":false,"wrapperOrigin":["Kamerun"],"fillerOrigin":["Nicaragua"],"binderOrigin":["Nicaragua"],"aromaProfileManufacturer":["Gras","Holz","Kaffee","Leder","Süß"],"strength":"Medium","flavourStrength":"Medium-aromatisch","smokingDuration":"45 bis 90 Min","price":9.2}
