{"name":"Leonel P-Series 640 Double Toro","url":"https://www.noblego.de/leonel-p-series-640-double-toro/","brand":"Leonel","series":"Leonel P-Series","details":{"Fazit":"Die Leonel P-Series 640 Double Toro steht für ausgedehnten Premiumgenuss der milden Art. Dass dabei der Geschmack nicht zu kurz kommt, liegt an ihren geduldig lang gereiften mittelamerikanischen Tabaken.","Genuss":"Dass die Leonel P-Series 640 Double Toro von bester Qualität ist, kann man bereits an ihrem feinem nicaraguanischen Connecticut Shade Deckblatt erkennen. In ihrer Einlage befindet sich eine raffinierte Mischung aus auf den Punkt gereiften und eher seltenen Panama Tabaken sowie ausgewählten Tabaken ihres Herkunftslandes Nicaragua. Von dort stammt auch das Umblatt der Leonel P-Series 640 Double Toro, die geschmacklich mit fruchtigen und nussigen Aromen, von einer leichten Süße begleitet, sehr zu überzeugen weiß. Die von Hand gerollte Longfiller Zigarre ist von absolut milder Natur, ein unaufdringlicher Smoke mit viel Geschmack und cremiger Rauchstruktur. Bei geradem Abbrand und auf das Format bestens eingestelltem Zug sorgt sie ungefähr 90 Minuten lang für einen entspannten und unkomplizierten Zigarrengenuss.","Hintergrund":"Qualität schreibt man im Hause Leonel besonders groß. An den zwei Produktionsstandorten in Nicaragua und der Dominikanischen Republik sind spezielle Teams jeweils für eine der verschiedenen Serien der Premiummarke verantwortlich. So garantiert man die gleichbleibend hohe Qualität der geschmackvollen Leonel Zigarren."},"diameter_mm":25.4,"ring":64,"length_mm":154,"length_inch":0,"format":"Double Toro","manufactureOrigin":"Nicaragua","construction":"Longfiller","isBoxpressed":false,"wrapperOrigin":["Nicaragua"],"fillerOrigin":["Nicaragua","Panama"],"binderOrigin":["Nicaragua"],"aromaProfileManufacturer":["Cremig","Fruchtig","Nuss","Süß"],"strength":"Mild","flavourStrength":"Mild-aromatisch","smokingDuration":"45 bis 90 Min","price":9.5}
