{"name":"Hernandez y Ruiz Half Corona","url":"https://www.noblego.de/hernandez-y-ruiz-half-corona/","brand":"Hernandez y Ruiz","series":"","details":{"Fazit":"Mit der mittelkräftigen Hernandez y Ruiz Half Corona liegt man immer richtig, wenn man auf der Suche nach einem nicht ganz so zeitintensiven Zigarrenformat ist. Greifen Sie zu und erleben Sie den besonderen Tabakgenuss aus dem wunderschönen Panama!","Genuss":"Die Hernandez y Ruiz Half Corona bringt Ihnen den etwas selteneren Genuss einer reinen Panama Zigarre nahe. Ihr feiner Blend besteht gänzlich aus Tabaken, die in den zwar rar gesäten, jedoch hervorragenden Anbaugebieten des mittelamerikanischen Landes unter besten Bedingungen gedeihen. Vordergründig sind es cremige Holz- und Grasnoten mit dezenter Süße kombiniert, die das Aromaaufkommen der handgerollten Longfiller bestimmen. Das Kleinformat wird zudem zu einem sehr annehmbaren Preis angeboten und schenkt Ihnen für bis zu 45 Minuten ein entspanntes und feinwürziges Rauchvergnügen. Währendessen können Sie sich voll und ganz auf den Genuss konzentrieren, denn bei Zug und Abbrand zeigt die delikate Panama Puro so gut wie gar keine Schwächen.","Hintergrund":"Die drei Formate der Hernandez y Ruiz Zigarren (Robusto, Short Corona, Half Corona) bieten Ihnen den außergewöhnlichen Genuss schmackhafter Panamatabake zu einem hervorragenden Preis-Leistungs-Verhältnis."},"diameter_mm":17.1,"ring":43,"length_mm":89,"length_inch":0,"format":"Half Corona","manufactureOrigin":"Panama","construction":"Longfiller","isBoxpressed":false,"wrapperOrigin":["Panama"],"fillerOrigin":["Panama"],"binderOrigin":["Panama"],"aromaProfileManufacturer":["Cremig","Gras","Holz","Süß"],"strength":"Medium","flavourStrength":"Medium-kräftig","smokingDuration":"20 bis 45 Min","price":5.1}
