{"name":"La Flor de Rosa Governor","url":"https://www.noblego.de/la-flor-de-rosa-governor/","brand":"La Flor de Rosa","series":"","details":{"Fazit":"Hier stimmt einfach alles, Qualität, Geschmack und Preis. Wer sich nicht an Bundleware stört, ist mit der La Flor de Rosa Governor gut beraten. Ein every day Smoke für Einsteiger und Fortgeschrittene, der gut mit einer Tasse Kaffee oder einem fruchtigen Rotwein harmoniert.","Genuss":"Mittelkräftig in der Stärke und medium-aromatisch im Geschmack ist die La Flor de Rosa Governor dennoch keine Durchschnittszigarre. Feinste Tabake aus Honduras und Nicaragua bestimmen das Aroma der 15,5 Zentimeter langen und 20 Millimeter dicken Toro. Dabei entfalten sich fruchtige Noten von Holz, Kaffee und Schokolade, die während der gesamten Rauchdauer von um die 70 Minuten präsent sind. Sie brennt zuverlässig und geht auch nicht aus, lässt man sie mal einige Minuten im Aschenbecher liegen. Der Zug ist durchweg angenehm leicht und auch der Abbrand gestaltet sich vorbildlich rund mit einer festen Asche.","Hintergrund":"Das Geschmacksgeheimnis der La Flor de Rosa Governor ist der Blend aus honduranischen und nicaraguanischen Tabaken in der Einlage, einem nicaraguanischen Umblatt und einem Deckblatt, das aus Sumatra Samen in Ecuador kultiviert wurde und für die leicht süßliche Note sorgt."},"diameter_mm":20,"ring":50,"length_mm":155,"length_inch":0,"format":"Toro","manufactureOrigin":"Nicaragua","construction":"Sandwichfiller","isBoxpressed":false,"wrapperOrigin":["Ecuador"],"fillerOrigin":["Honduras","Nicaragua"],"binderOrigin":["Nicaragua"],"aromaProfileManufacturer":["Fruchtig","Holz","Kaffee","Schokolade"],"strength":"Medium","flavourStrength":"Medium-aromatisch","smokingDuration":"45 bis 90 Min","price":2.7}
