{"name":"Alec Bradley Raices Robusto","url":"https://www.noblego.de/alec-bradley-raices-robusto/","brand":"Alec Bradley","series":"Alec Bradley Raices","details":{"Fazit":"Hier stimmt einfach alles. Die Alec Bradley Raices Robusto ist eine würzige Zigarre von ausgezeichneter Qualität. Ein wirklich gelungenes Erstlingswerk.","Genuss":"Die Fabrica de Tabacos Raices ist für ihre hochwertige Handarbeit bekannt, die vielen Zigarrenmarken erst zu ihrem Ruhm verholfen hat. Da war es nur eine Frage der Zeit, bis sich die Familie Endemano an eine eigene Tabakkreation wagen würde. Herausgekommen ist die Raices 1941. Die Jahreszahl steht für das Geburtsdatum von Fabrikinhaber Romay Endemano. Als Vertriebspartner und teilhabenden Finanzier wählte man Alan Rubin. Daher kann die Zigarre auch unter dem Label von Alec Bradley laufen. Die Alec Bradley Raices Robusto ist eine mittelkräftige Zigarre, die zum Finish noch etwas an Stärke zulegt. Das Deckblatt stammt aus Honduras, das Umblatt aus Nicaragua. Die Einlage besteht aus Longfiller-Tabaken aus Honduras und Nicaragua. Die Robusto misst eine Länge von 133 mm bei einem Ringmaß von 52. Ihr Zigarrenkopf ist mit einer dreifachen Kappe abgeschlossen, was auch oft bei kubanischen Zigarren der Fall ist. Aromatisch erinnert der Blend zu Beginn an weißen Pfeffer, Getreide und etwas Toffee. Im zweiten Drittel kommen erdige Noten hinzu, die im letzten Drittel noch präsenter werden und mit Leder und einer leichten Pfeffrigkeit ein würziges Finale bilden. Gerade zum Schluss bietet es sich, ob der zunehmenden Stärke an, die Raices Robusto etwas langsamer zu rauchen. So kommen gut 60 Minuten und mehr Rauchdauer zusammen.","Hintergrund":"Vorgestellt wurden die Raices Zigarren erstmalig auf der IPCPR 2013 am Stand von Alec Bradley. Die Zusammenarbeit von Alec Bradley und Raices besteht schon seit 1990. Unter anderem werden in der Manufaktur die Alec Bradley Serien \u003ca title=\"Hier geht's zu den Alec Bradley Mundial Zigarren\" href=\"/alec-bradley-mundial-zigarren/\"\u003eMundial\u003c/a\u003e, \u003ca title=\"Hier geht's zu den Alec Bradley Prensado Zigarren\" href=\"/alec-bradley-prensado-zigarren/\"\u003ePrensado\u003c/a\u003e und \u003ca title=\"Hier geht's zu den Alec Bradley The Lineage Zigarren\" href=\"/alec-bradley-family-blend-the-lineage-zigarren/\"\u003eThe Lineage\u003c/a\u003e produziert."},"diameter_mm":20.6,"ring":52,"length_mm":133,"length_inch":0,"format":"Robusto","maker":"Alan Rubin","manufactureOrigin":"Honduras","construction":"Longfiller","wrapperOrigin":["Honduras"],"fillerOrigin":["Honduras","Nicaragua"],"binderOrigin":["Nicaragua"],"aromaProfileManufacturer":["Cremig","Erdig","Leder","Pfeffer","Toffee"],"strength":"Medium","flavourStrength":"Medium-kräftig","smokingDuration":"45 bis 90 Min","price":8.5}
