{"name":"Casa Culinaria Red Corona","url":"https://www.noblego.de/casa-culinaria-red-corona/","brand":"Casa Culinaria","series":"Red","details":{"Fazit":"Die Casa Culinaria Red Corona ist eine starke, geschmacklich sehr interessante Zigarre, die zu vielen Gelegenheiten passt. Sie schmeckt hervorragend zu einem gut gekühlten Bier und macht den Feierabend damit perfekt.","Genuss":"Die Casa Culinaria Red Corona lockt bereits im Kaltgeruch mit einer zarten Note von sehr guter Schokolade. Sie ist handwerklich einwandfrei, sehr fest gerollt und das richtig ölige Maduro-Deckblatt sieht vielversprechend aus. Es ist ein edles Caribbean-Ecuador-Deckblatt, das für den leicht karamelligen Unterton bei dieser Zigarre sorgt. Für die Einlage der Casa Culinaria Red Corona wurden mehrere Tabaksorten aus Nicaragua ausgewählt. Das Umblatt ist ein Exemplar aus Indonesien, das erdige Töne mitbringt und den Charakter der Casa Culinaria Red Corona harmonisch abrundet. Insgesamt führt diese Kreation zu einem interessanten und dabei gut balancierten Geschmack nach Gras, Minze und Schokolade. Der Zugwiderstand ist spürbar und gut, diese Corona brennt ganz gleichmäßig ab. Die Casa Culinaria Red Corona besitzt eine Länge von 136 Millimetern und einen Durchmesser von 16 Millimetern. Damit kommt man mit diesem handlichen Format auf eine Rauchdauer von etwa 40 Minuten.","Hintergrund":"Die Casa Culinaria Red Serie kommt aus der Manufaktur Casa de Alegria. Dieses traditionsreiche Unternehmen stellt seit Jahrzehnten in Nicaragua hochwertige Zigarren her. Diese haben sich auf dem internationalen Markt etablieren können. Geschmack und Aromen haben viele Aficionados in aller Welt überzeugt. In Nicaragua gibt es mehrere Anbaugebiete, in denen der Tabak unter genauen Kontrollen heranreift.  Bei den Zigarren dieser Serie handelt sich stets um Mediumfiller. Ihre Einlage wird aus denselben wertvollen Tabaken gefertigt, wie sie in der Longfiller-Produktion verwendet werden."},"diameter_mm":16,"ring":40,"length_mm":136,"length_inch":0,"format":"Corona","manufactureOrigin":"Nicaragua","construction":"Mediumfiller","isBoxpressed":false,"wrapperOrigin":["Ecuador"],"fillerOrigin":["Nicaragua"],"binderOrigin":["Indonesien"],"aromaProfileManufacturer":["Erdig","Gras","Minze","Schokolade"],"strength":"Stark","flavourStrength":"Mild-aromatisch","smokingDuration":"45 bis 90 Min","price":2.1}
