{"name":"Leonel P-Series 550 Robusto","url":"https://www.noblego.de/leonel-p-series-550-robusto/","brand":"Leonel","series":"Leonel P-Series","details":{"Fazit":"Mit der Leonel P-Series 550 Robusto kommt eine milde mittelamerikanische Zigarre zu Ihnen nach Hause, die sowohl geschmacklich als auch preislich überzeugt.","Genuss":"Das „P“ im Namen der Leonel P-Series 550 Robusto steht für den fünf Jahre lang gereiften Panama Tabak, der sich zusammen mit ebenfalls sorgsam gereiften nicaraguanischen Tabaken in der bestens verarbeiteten Vitola befindet. Geschmacklich führt diese zentralamerikanische Mischung zu einer cremig fruchtigen und nussigen Aromaentwicklung mit leicht süßlichen Noten. Vom Rauchstart an sind diese delikaten Töne präsent und begleiten den milden Genuss der Robusto bis zum letzten Zentimeter angenehm klar und unaufdringlich. Die handgerollte Longfiller weist zudem einen auf ihr Format bestens eingestellten Zug auf. Beim Abbrand bereitet die geschmackvolle Nicaraguanerin dem Genießer ebenfalls keinerlei Probleme.","Hintergrund":"Die Zigarren der Marke Leonel wurden bereits mehrfach für ihre hervorragende Qualität ausgezeichnet. Gerollt werden die leckeren Smokes der Leonel P-Series in der Zigarrenhauptstadt Nicaraguas, Estelí, die einige Hundert Kilometer nördlich des nicaraguanischen Regierungssitzes Managua gelegen ist."},"diameter_mm":20.6,"ring":52,"length_mm":139,"length_inch":0,"format":"Robusto","manufactureOrigin":"Nicaragua","construction":"Longfiller","isBoxpressed":false,"wrapperOrigin":["Nicaragua"],"fillerOrigin":["Nicaragua","Panama"],"binderOrigin":["Nicaragua"],"aromaProfileManufacturer":["Cremig","Erdig","Fruchtig","Nuss"],"strength":"Mild","flavourStrength":"Mild-aromatisch","smokingDuration":"45 bis 90 Min","price":6.6}
