{"name":"Flor de Copan Linea Puros Churchill","url":"https://www.noblego.de/flor-de-copan-linea-puros-churchill/","brand":"Flor de Copan","series":"Linea Puros","details":{"Fazit":"Wenn es länger dauern soll und ein Rotwein sowieso schon lange auf der Liste stand, dann ist die Flor de Copan Linea Puros Churchill die perfekte Wahl.","Genuss":"Schon die Kiste der Flor de Copan Linea Puros Churchill ist ein Hingucker der Extraklasse. Jede der 20 Zigarren ist in ihrem eigenen Fach untergebracht, die 2 Tabletts lassen sich jeweils herausnehmen und so gut präsentieren, zum Beispiel beim Pokerabend mit Freunden. Die honduranische Churchill misst klassische 178 x 19 mm und taugt daher locker für 90 Minuten Rauchgenuss. Das ist auch so weil die Churchill, ähnlich wie die Corona, etwas dichter gerollt ist und einen stärkeren, jedoch nicht unangenehmen, Zugwiderstand besitzt. Medium-stark mit Aromen von Kaffee, Schokolade, Zedernholz, Nuss und Leder sowie einem süß und cremigen erscheinenden Rauch. Der Abbrand ist sehr gut und gerade, alles in Allem ist die Zigarre eine wunderbare Abwechslung für sowohl Liebhaber milder als auch der stärkerer Zigarren, da Sie die Mitte wie kaum eine andere besetzt.","Hintergrund":"Rund um die Provinzhauptstadt Santa Rosa de Copan wird der Tabak für diese Blume von Copan angebaut. Das Hochland an der nördlichen Grenze zu Guatemala hat ein unverwechselbares Klima und ist zusätzlich für seinen Kaffee bekannt. Nichts in dieser Zigarre kommt nicht von hier, eine Puro eben."},"diameter_mm":19,"ring":48,"length_mm":178,"length_inch":0,"format":"Churchill","manufactureOrigin":"Honduras","construction":"Longfiller","isBoxpressed":false,"wrapperOrigin":["Honduras"],"fillerOrigin":["Honduras"],"binderOrigin":["Honduras"],"aromaProfileManufacturer":["Cremig","Kaffee","Leder","Nuss","Schokolade","Süß","Würzig","Zedernholz"],"strength":"Medium","flavourStrength":"Medium-aromatisch","smokingDuration":"45 bis 90 Min","price":9.3}
