{"name":"CAO La Traviata Animado","url":"https://www.noblego.de/cao-la-traviata-animado/","brand":"CAO","series":"La Traviata","details":{"Fazit":"Ob die CAO La Traviata Animado belebend wirkt wie ihr Name vermuten lässt, müssen Sie selber entscheiden. Uns hat die starke Corona jedenfalls mit ihrer guten Verarbeitung und den wunderbar komplexen und harmonischen Aromen überzeugt. Für den Preis ein Smoke, den man sich auch mal öfter leisten kann.","Genuss":"Die CAO La Traviata Animado liegt mit ihren 14 Zentimetern Länge und einem Durchmesser von 17 Millimetern gut in der Hand und ist haptisch ganz Premiumzigarre. Der Blend besteht aus Tabaken aus vier verschiedenen Länder. Ein ecuadorianisches Colorado Deckblatt umschließt das Umblatt aus Kamerun, für die Einlage werden dominikanische und nicaraguanische Tabake verarbeitet. Während der Rauchdauer von 70 bis 80 Minuten entfaltet die Corona würzige Aromen, die mit Zedernholz-, Leder- und Schokoladenoten aufwarten. Zur Mitte treten pfeffrige Noten verbunden mit Röstaromen zunehmend in den Vordergrund, dennoch wird der Longfiller zu keiner Zeit unangenehm scharf, sondern nimmt am Ende des Smokes nochmal an Cremigkeit zu. Der gute Zug und das gleichmäßige Abbrennverhalten bestätigen die erstklassige Verarbeitung und runden den einzigartigen CAO-Genuss optimal ab.","Hintergrund":"\u003ca title=\"Hier gehts zur CAO Brazilia\" href=\"/cao-brazilia-zigarren/\"\u003eBrazilia\u003c/a\u003e, \u003ca title=\"Hier gehts zur CAO OSA\" href=\"/cao-osa-zigarren/\"\u003eOSA\u003c/a\u003e, \u003ca title=\"Hier gehts zur CAO Gold\" href=\"/cao-gold-zigarren/\"\u003eGold\u003c/a\u003e, \u003ca title=\"Hier gehts zur CAO Italia\" href=\"/cao-italia-zigarren/\"\u003eItalia\u003c/a\u003e oder La Traviata - CAO hat viele unterschiedliche Serien im Sortiment, die in verschiedenen Ländern Südamerikas gefertigt werden und die jeweils heimischen Tabake verarbeiten. Das Konzept geht auf, CAO Zigarren sind mittlerweile fest auf dem internationalen Markt etabliert und haben einige ausgezeichnete Formate in ihren Reihen."},"diameter_mm":17,"ring":42,"length_mm":141,"length_inch":0,"format":"Corona","manufactureOrigin":"Nicaragua","construction":"Longfiller","isBoxpressed":false,"wrapperOrigin":["Ecuador"],"fillerOrigin":["Dominikanische Republik","Nicaragua"],"binderOrigin":["Kamerun"],"aromaProfileManufacturer":["Leder","Pfeffer","Schokolade","Zedernholz"],"strength":"Stark","flavourStrength":"Medium-aromatisch","smokingDuration":"45 bis 90 Min","price":5.8}
