{"name":"Rocky Patel Tabaquero by Hamlet Paredes Robusto","url":"https://www.noblego.de/rocky-patel-tabaquero-by-hamlet-paredes-robusto/","brand":"Rocky Patel","series":"Tabaquero by Hamlet Paredes","details":{"Fazit":"Hamlet Paredes hat’s drauf. Aber anders war das auch eigentlich nicht zu erwarten. Mit der Tabaquero by Hamlet Paredes Robusto und ihren Geschwistern vollzieht er erfolgreich den Wandel vom Torcedor zum Masterblender.","Genuss":"Wer es vollmundig und komplex mag, wird an der Rocky Patel Tabaquero by Hamlet Paredes Robusto nicht vorbeikommen. Schon das sehr dunkle, ölige Deckblatt mit dem Geruch nach Schokolade und Kakao lässt erahnen, welch ein Smoke hier darauf wartet endlich verköstigt zu werden. Und die Erwartungen werden nicht enttäuscht. Zu Beginn erdig mit dunkler Schokolade, etwas Süße und Pfeffer, im Verlauf auch Kakao, Zedernholz und Lakritz. Immer wieder kommt das erdige Aroma durch, das aber weiterhin von den süßlicheren Aromen konterkariert wird. Die Robusto bewegt sich auf medium-starkem bis starkem Terrain, überfordert aber nicht. Sie verbindet geschickt kubanische Tradition mit den Aromen Nicaraguas und Mexikos mit einem Hauch Brasilien. Mit den klassischen Maßen von 127 mm Länge und 19,8 mm Durchmesser bietet sie ein Genusserlebnis von bis zu 60 Minuten, das gefühlt aber auch gerne länger andauern könnte. Mit den größeren Formaten der Serie \u003ca title=\"Hier geht's zur Tabaquero Salomon\" href=\"/rocky-patel-tabaquero-by-hamlet-paredes-salomon/\"\u003eSalomon\u003c/a\u003e oder \u003ca title=\"Hier geht's zur Tabaquero Toro\" href=\"/rocky-patel-tabaquero-by-hamlet-paredes-toro/\"\u003eToro\u003c/a\u003e ist das ohne Probleme möglich.","Hintergrund":"Kubanischer Genuss mit den Tabaken Nicaraguas, nichts weniger ist das Ziel der Serie Tabaquero by Hamlet Paredes. Und man muss schon sagen, die Zigarren kommen nah ran an den kubanischen Geschmack. Die Einlage stammt aus Nicaragua, das Deckblatt aus Mexiko. Ganze zwei Umblätter werden verarbeitet – eins aus Mexiko, eins aus Brasilien."},"diameter_mm":19.8,"ring":50,"length_mm":127,"length_inch":0,"format":"Robusto","maker":"Hamlet Paredes","manufactureOrigin":"Nicaragua","construction":"Longfiller","isBoxpressed":false,"wrapperOrigin":["Mexico"],"fillerOrigin":["Nicaragua"],"binderOrigin":["Brasilien","Mexican San Andres"],"aromaProfileManufacturer":["Erdig","Lakritz","Pfeffer","Schokolade","Zedernholz"],"strength":"Medium","flavourStrength":"Medium-aromatisch","smokingDuration":"45 bis 90 Min","price":10.2,"additionalNotes":"Doppeltes Umblatt"}
