{"name":"Asylum Schizo Robusto","url":"https://www.noblego.de/asylum-schizo-robusto/","brand":"Asylum","series":"Schizo","details":{"Fazit":"Die Asylum Schizo Robusto Zigarren zeigen sich durchaus als temperamentvoll, außerdem ergiebig und überzeugend im Geschmack und in den Aromen. Dazu passt sehr gut ein gut ausgereifter Rotwein aus Südamerika.","Genuss":"Asylum Schizo Robusto sind charaktervolle Puro-Zigarren aus Nicaragua. Es sind mittelkräftige und überraschend aromatische Zigarren. Schon im Kaltgeruch verspürt man den Duft von gegerbtem Sattelleder. Im Rauch präsentieren sich diese Puros aus Nicaragua leicht cremig, etwas holzig und mit einer zart süßlichen Note. Auch der Duft nach Leder ist wieder zu spüren. Die tadellose Verarbeitung zeigt sich nicht nur im Deckblatt, sondern in allen Schichten. Fest gerollt bietet sie einen guten Zugwiderstand, der zum langsamen Genießen einlädt. Bei fast 20 Millimetern Durchmesser und 127 Millimetern Länge hält der vielschichtige Rauchgenuss dieses Sandwichfillers eine Stunde lang an.","Hintergrund":"Unter der Marke Asylum werden einige Formate von Sandwichfillern angeboten. Diese Zigarren werden zudem noch im Bundle geliefert und sind deshalb besonders günstig. Gut verarbeitete und hochwertige Tabake können zu einem sehr erschwinglichen Preis angeboten werden. Dabei stehen sie Longfiller-Marken im Geschmack in nichts nach. Die Sandwich-Einlage wirkt sich in der Regel sehr positiv auf das Abbrand- und Zugverhalten aus, weil die enthaltenen Shortfiller-Stückchen die Zigarren sehr gut am Glimmen halten."},"diameter_mm":19.8,"ring":50,"length_mm":127,"length_inch":0,"format":"Robusto","manufactureOrigin":"Nicaragua","construction":"Sandwichfiller","isBoxpressed":false,"wrapperOrigin":["Nicaragua"],"fillerOrigin":["Nicaragua"],"binderOrigin":["Nicaragua"],"aromaProfileManufacturer":["Holz","Kakao","Leder","Süß"],"strength":"Medium","flavourStrength":"Medium-aromatisch","smokingDuration":"20 bis 45 Min","price":3.4}
