{"name":"La Flor Dominicana Capitulo II","url":"https://www.noblego.de/la-flor-dominicana-capitulo-ii/","brand":"La Flor Dominicana","series":"","details":{"Fazit":"Die La Flor Dominicana Capitulo II ist eine absolut gelungene Fortsetzung der Chapter One und macht jetzt schon Lust auf das nächste Kapitel.","Genuss":"Auch in seinem zweiten Kapitel lässt Antonio Gomez keinen Zweifel daran, was er von seinem Vater gelernt und an Talent geerbt hat. Der hervorragend verarbeitete Longfiller ist wie die \u003ca title=\"Hier geht's zur La Flor Dominicana Chapter One\" href=\"/la-flor-dominicana-chapter-one/\"\u003eLa Flor Dominicana Chapter One\u003c/a\u003e boxpressed und mit einem Zigarrenkopf in Chiselform ausgestattet. Sie können den Anschnitt also ganz individuell gestalten. Der Blend besteht aus einem rotbraunem nicaraguanischen Colorado Deckblatt, einem ecuadorianischen Caribbean Umblatt und einer Einlage aus der Dominikanischen Republik und entwickelt sich im Rauchverlauf von mittelstark zu stark. Schon der Kaltgeruch nach Erde und Leder lässt die Würze der La Flor Dominicana Capitulo II erahnen. Der Kaltzug offenbart zusätzlich holzige und pfeffrige Noten. Die Zigarre ist gleich nach dem Anzünden aromatisch sehr präsent und wird im ersten Drittel dominiert von Erde, Mandel, Leder, etwas Saffran, etwas Salz und einer ordentlichen Portion Pfeffer. Im zweiten Drittel sind nur wenige aromatische Veränderungen wahrzunehmen, erst im letzten Drittel kommt mit Kakao und einer deutlicheren Süße eine interessante Variation des Aromenspektrums hervor. Bei einer Länge von 165 mm und einem Durchmesser von 23 mm ist eine lange Rauchdauer zu erwarten. Da sich die LFD Capitulo II wunderbar bis hinter den Zigarrenring rauchen lässt, sind sogar bis zu zwei Stunden möglich. Zug und Abbrand bleiben über den gesamten Rauchverlauf mustergültig.","Hintergrund":"Für die zweite Zigarre von Antonio Gomez wurde diesmal der spanische Name „Capitulo Dos“ anstatt des englischen „Chapter Two“ gewählt, um Verwechslungen mit der Casa Miranda Chapter Two zu vermeiden, die ein Jahr zuvor erschienen ist. Rund 100.000 Exemplare der La Flor Dominicana Capitulo II wurden produziert und in 10er Boxen verschickt.\nCigar Aficionado bewertete diesen kräftigen Smoke direkt mit 90 Punkten. Das Cigar Journal zog in der Sommerausgabe 2015 nach und vergab ebenfalls 90 Punkte und das Prädikat \"Best Buy\"."},"diameter_mm":23,"ring":58,"length_mm":165,"length_inch":0,"format":"Double Toro","maker":"Antonio Gomez","manufactureOrigin":"Dominikanische Republik","construction":"Longfiller","isBoxpressed":true,"wrapperOrigin":["Nicaragua"],"fillerOrigin":["Dominikanische Republik"],"binderOrigin":["Ecuador"],"aromaProfileManufacturer":["Erdig","Gewürze","Holz","Leder","Pfeffer","Süß"],"strength":"Stark","flavourStrength":"Medium-kräftig","smokingDuration":"90 Min oder länger","price":11,"additionalNotes":"Chisel"}
