{"name":"Vega Fina Nicaragua Robusto","url":"https://www.noblego.de/vega-fina-nicaragua-robusto/","brand":"Vega Fina","series":"Vega Fina Nicaragua","details":{"Fazit":"Eine Nicaraguanerin aus der Dominikanischen Republik: die Vega Fina Nicaragua Robusto ist definitiv einen Smoke wert. Und einen zweiten. Und einen dritten….","Genuss":"Während die bisherigen Serien der Vega Fina Zigarren eher für ihre milden Noten bekannt sind, bekommt man es bei der Vega Fina Nicaragua Robusto mit einer eher mittelkräftigen bis kräftigen Zigarre zu tun. Das liegt eindeutig an ihren ausschließlich nicaraguanischen Tabaken, die eine würzige Note in den Smoke einfließen lassen. Der Kaltgeruch zeigt sich süßlich mit Noten von Schokolade und Holz. Beides findet sich auch während des Rauchgenusses wieder. Dazu gesellen sich zarte Anklänge von Kaffee, Nuss und Röstaromen. Die klassischen Robustomaße von 127 mm Länge und 19,8 mm Durchmesser versprechen ein Genusserlebnis von 40 bis 50 Minuten. Der Abbrand kann sich hier und da etwas uneben gestalten, wirkt sich aber nicht negativ auf den Smoke aus und lässt sich gut korrigieren. Das perfekte Zugverhalten offenbart wiederum die hochwertige Verarbeitung des Longfillers.","Hintergrund":"Die Marke Vega Fina ist besonders in Spanien beliebt. Dort ist sie die meistverkaufte Zigarre, die nicht aus Kuba stammt. Sie gehört zum Portfolio der Schweizer Villiger und Söhne Holding AG, die auch Marken wie \u003ca title=\"Hier geht's zu den Joya de Nicaragua Zigarren\" href=\"/joya-de-nicaragua-zigarren/\"\u003eJoya de Nicaragua\u003c/a\u003e, \u003ca title=\"Hier geht's zu den Casa de Nicaragua Zigarren\" href=\"/casa-de-nicaragua-zigarren/\"\u003eCasa de Nicaragua\u003c/a\u003e oder \u003ca title=\"Hier geht's zu den La Capitana Zigarren\" href=\"/la-capitana-zigarren/\"\u003eLa Capitana\u003c/a\u003e vertreibt."},"diameter_mm":19.8,"ring":50,"length_mm":127,"length_inch":0,"format":"Robusto","manufactureOrigin":"Dominikanische Republik","construction":"Longfiller","isBoxpressed":false,"wrapperOrigin":["Nicaragua"],"fillerOrigin":["Nicaragua"],"binderOrigin":["Nicaragua"],"aromaProfileManufacturer":["Holz","Kaffee","Nuss","Röstaromen","Süß"],"strength":"Medium","flavourStrength":"Medium-aromatisch","smokingDuration":"45 bis 90 Min","price":7}
