{"name":"Thomas Hinds Churchill Natural","url":"https://www.noblego.de/thomas-hinds-churchill-natural/","brand":"Thomas Hinds","series":"","details":{"Fazit":"Ein schöner Smoke für die ausgedehnte Kaffeepause am Nachmittag oder auch zum Feierabend. Dazu ein Café Latte oder ein India Pale Ale und der Genuss ist perfekt.","Genuss":"In der Thomas Hinds Churchill Natural vereinigen sich verschiedene Tabake aus Honduras, die für die Einlage und das Umblatt verwendet werden und ein Deckblatt aus Ecuador. Mit Maßen von 177 mm  Länge und 19 mm Durchmesser handelt es sich um ein klassisches Churchill-Format, das eine Rauchdauer bis zu Anderthalbstunden bietet. Mittelkräftig in der Stärke entwickelt sich ein angenehmer Smoke, der recht komplex im Aroma daherkommt. Typisch Honduras mit würziger Erde und Pfeffer, aber auch Holz, Nuss und fruchtig-süßen Anklängen. Der Abbrand ist gerade, es kann jedoch passieren, dass die Thomas Hinds Churchill Natural zwischendrin nachgefeuert werden muss. Das Zugverhalten präsentiert sich hingegen nahezu perfekt. Die Asche tendiert zu einem dunkleren Grauton und hält durchaus ein ganzes Stück des Rauchweges.","Hintergrund":"Thomas Hinds ist ein kleiner Zigarren-, Pfeifen- und Tabakshop im Herzen Torontos. Dort kann man neben vielen anderen Produkten natürlich auch die hauseigenen Thomas Hinds Zigarren erstehen. Für den Vertrieb in Deutschland sorgt der Saarbrücker Zigarrenhandel Dalay Zigarren."},"diameter_mm":19,"ring":48,"length_mm":177,"length_inch":0,"format":"Churchill","manufactureOrigin":"Honduras","construction":"Longfiller","isBoxpressed":false,"wrapperOrigin":["Ecuador"],"fillerOrigin":["Honduras"],"binderOrigin":["Honduras"],"aromaProfileManufacturer":["Fruchtig","Holz","Nuss","Süß"],"strength":"Medium","flavourStrength":"Medium-aromatisch","smokingDuration":"45 bis 90 Min","price":6.5}
