{"name":"Alec Bradley Project 40 Robusto","url":"https://www.noblego.de/alec-bradley-project-40-robusto-zigarren/","brand":"Alec Bradley","series":"Project 40","details":{"Genussverlauf":"Ein makellos erscheinendes nicaraguanisches Deckblatt, unter dem ein brasilianisches Sun Grown Umblatt sowie verschiedene Einlagetabake aus Nicaragua liegen, bilden den Blend der Alec Bradley Project 40 Robusto. Die in der Manufaktur Jesus Fuegos von Hand gerollte Longfiller startet angenehm mild und entwickelt einen wunderbar voluminösen Rauch. Ihr durchaus komplex wirkendes Aromaaufkommen wird von einer cremigen Mandelnote und leckeren Rosinensüße bestimmt, zu denen sich delikate Erd-, Toast-, Zedernholz- und Kakaotöne gesellen. Auf retronasaler Ebene lassen sich zudem verschiedene Gewürzaromen und Nuancen weißen Pfeffers ausmachen. Die mit einem perfekten Zugverhalten aufwartende Robusto nimmt im Rauchverlauf etwas an Stärke zu, bleibt jedoch bis zum Ende im gemäßigt mittelkräftigen Bereich.","Nice to know":"Alan Rubin, Unternehmensgründer der Alec Bradley Cigar Company, wurde von einer internationalen Studie, welche sich mit dem Glücklichsein von Menschen befasst, zu der Project 40 Serie inspiriert. Im Rahmen der besagten Studie stellte man die These auf, das Glücksempfinden der Menschen sei zu 50 Prozent von ihrer Genetik, zu 10 Prozent von ihren jeweiligen Lebensumständen und zu 40 Prozent von ihrer Form der Lebens- sowie Denkweise abhängig. Dem zuletzt genannten Wert ordnete Rubin folgerichtig den Genuss von Zigarren zu und integrierte ihn kurzerhand in den Namen der delikaten Project 40 Zigarrenserie.","Resümee":"Wir benötigen keine Studie, um zu wissen, dass gute Zigarren eine zufriedenstellende und entspannende Wirkung auf ihre Genießer ausüben. Wir wissen allerdings auch nicht, ob Sie die Alec Bradley Project 40 Robusto glücklicher machen wird. Aber dass Sie Ihnen schmecken wird, davon sind wir überzeugt."},"diameter_mm":19.8,"ring":50,"length_mm":127,"length_inch":0,"format":"Robusto","manufactureOrigin":"Nicaragua","construction":"Longfiller","isBoxpressed":false,"wrapperOrigin":["Nicaragua"],"fillerOrigin":["Nicaragua"],"binderOrigin":["Brasilien"],"aromaProfileManufacturer":["Cremig","Erdig","Gewürze","Kakao","Mandel","Rosine","Toast","Weißer Pfeffer","Zedernholz"],"smokingDuration":"45 bis 90 Min","price":7}
