{"name":"Pinar Tabacos Anejados Rothschild","url":"https://www.noblego.de/pinar-tabacos-anejados-rothschild/","brand":"Pinar Tabacos Anejados","series":"","details":{"Fazit":"Für Zigarrenliebhaber, die gerne einmal etwas anderes probieren möchten, sind Pinar Tabacos Anejados Zigarren ganz bestimmt eine Empfehlung. Sie sind mild und erzielen durch ihre zurückhaltenden Aromen eine gewisse Eleganz im Rauchgenuss. In der Kiste sind sie auch ein sehr attraktives Geschenk.","Genuss":"Pinar Tabacos Añejados Zigarren bestehen komplett aus Tabaken Ecuadors. Sie sind sehr angenehm im Geschmack, lassen sich aber nur schwer mit bekannten Vertretern karibischer Zigarren vergleichen. Die ecuadorianischen Tabake sind dunkel, edel und sehr mild. Die Verarbeitung dieses Longfillers ist tadellos. Die fest gerollte Zigarre leistet einen guten Zugwiderstand. Tabakgeschmack pur ist vielleicht die beste Umschreibung dieses milden Smokes. Die Pinar Tabacos Anejados Rothschild entspricht einer Gran Corona und hat eine Länge von 153 mm und ein Ringmaß von 48. Damit bietet sie ein Rauchvergnügen von einer guten Stunde. Sie wird von uns einzeln oder in einer sehr schön gearbeiteten Massivholzkiste geliefert.","Hintergrund":"Tabak aus Ecuador wird bei dieser Zigarre nicht nur im Deckblatt verwendet, sondern für alle Lagen. Die klimatischen Bedingungen Ecuadors sind ganz ausgezeichnet für den Tabakanbau geeignet. Wolken, Wolken und nochmals Wolken, die sich an den Hängen der Anden abregnen, kommen dem Tabak sehr zu Gute. Tabakbauern kommen hier ohne künstliche Schattierung aus, um die Pflanzen vor zu kräftiger Sonneneinstrahlung zu schützen. Dies wirkt sich sehr positiv auf Farbe und Würze des Tabaks aus."},"diameter_mm":19,"ring":48,"length_mm":153,"length_inch":0,"format":"Gran Corona","manufactureOrigin":"Ecuador","construction":"Longfiller","isBoxpressed":false,"wrapperOrigin":["Ecuador"],"fillerOrigin":["Ecuador"],"binderOrigin":["Ecuador"],"strength":"Mild","flavourStrength":"Medium-aromatisch","smokingDuration":"45 bis 90 Min","price":4.9,"additionalNotes":"Aged"}
