{"name":"Mombacho Tierra Volcan Clasico","url":"https://www.noblego.de/mombacho-tierra-volcan-clasico/","brand":"Mombacho","series":"","details":{"Fazit":"Eine Zigarre wie die Mombacho Tierra Volcan Clasico bedeutet eine absolute Bereicherung für unseren heimischen Genussmarkt. Unbedingt probieren!","Genuss":"Alle Tabake der Mombacho Tierra Volcan Clasico stammen aus dem nicaraguanischen Grenada, das nahe zum größten Vulkan des Landes, dem Mombacho, gelegen ist. Diese Region ist bekannt für die fruchtbare und mineralreiche Vulkanerde, auf der die hervorragenden Tabake für die mittelkräftigen bis kräftigen Premiumzigarren gedeihen. Bei der Tierra Volcan Clasico handelt es sich um ein etwas verlängertes Robusto Format (14 cm), welches über einen sahnig-cremigen Rauch, intensive von pikanter Würze umwobene Kakao-, Nuss-, Leder- und Kaffeearomen bietet. Zusätzlich werden diese von einer besonders delikaten süß-erdigen Note umspielt. Insgesamt ein anspruchsvoller Smoke für gestandene Genießer, die komplexe und vollmundige Zigarren aus Nicaragua zu schätzen wissen. Zug- und Abbrandverhalten der schmackhaften Longfiller können als absolut problemlos bezeichnet werden.","Hintergrund":"Produziert werden die Mombacho Zigarren seit 2014 in der gleichnamigen Manufaktur. Zunächst wurden die eindrucksvollen Premiumzigarren nur auf dem amerikanischen Markt angeboten. Seit Anfang dieses Jahres gibt es sie nun auch bei uns in Deutschland, wo sie bereits nach kurzer Zeit einige Liebhaber für sich gewinnen konnten."},"diameter_mm":19.8,"ring":50,"length_mm":140,"length_inch":0,"format":"Robusto Extra","manufactureOrigin":"Nicaragua","construction":"Longfiller","isBoxpressed":false,"wrapperOrigin":["Nicaragua"],"fillerOrigin":["Nicaragua"],"binderOrigin":["Nicaragua"],"aromaProfileManufacturer":["Cremig","Erdig","Kaffee","Kakao","Leder","Nuss","Süß","Würzig"],"strength":"Medium","price":9.3}
