{"name":"Alec Bradley Project 40 Toro","url":"https://www.noblego.de/alec-bradley-project-40-toro-zigarren/","brand":"Alec Bradley","series":"Project 40","details":{"Genussverlauf":"Bis auf ihr brasilianisches Umblatt stammen alle Tabake der Alec Bradley Project 40 Toro von nicaraguanischen Plantagen. Für die Fertigung per Hand ist die Zigarrenmanufaktur von Jesus Fuegos verantwortlich. Die Toro präsentiert sich zu Anfang des Genusses angenehm mild. Sie entwickelt eine ganze Fülle cremigen Rauchs, der abwechslungsfreudige Aromen von Zedernholz, Erde, Kakao und Toast an den Gaumen des Genießers trägt. Feine Noten von Mandel und eine sanfte Rosinensüße mischen sich zusätzlich in dem etwa 80 Minuten andauernden Rauchverlauf unter die oben genannten Aromen. Bei Zugverhalten und Abbrand zeigt sich die sehr gut verarbeitete Longfiller-Zigarre vorbildlich.","Nice to know":"Die Alec Bradley Project 40 Serie besteht insgesamt aus drei Formaten, einer Toro, Gordo und Robusto. Gut möglich, dass in nächster Zeit noch ein weiteres Format hinzukommt, eventuell eine schlanke Corona für Freunde des etwas kürzeren Rauchgenusses.","Resümee":"Eine schmackhafte Zigarre wie die Alec Bradley Project 40 Toro bietet sich besonders gut für Zigarreneinsteiger an, die sich an etwas kräftigere Blends heranwagen möchten. Denn die Toro startet anfänglich mild, entwickelt sich dann aber Zug um Zug bis hin zu einer mittelkräftigen Stärke."},"diameter_mm":20.6,"ring":52,"length_mm":152,"length_inch":0,"format":"Toro","manufactureOrigin":"Nicaragua","construction":"Longfiller","isBoxpressed":false,"wrapperOrigin":["Nicaragua"],"fillerOrigin":["Nicaragua"],"binderOrigin":["Brasilien"],"aromaProfileManufacturer":["Cremig","Erdig","Gewürze","Kakao","Mandel","Rosine","Toast","Weißer Pfeffer","Zedernholz"],"smokingDuration":"90 Min oder länger","price":7.8}
