{"name":"New World by A.J. Fernandez Gobernador","url":"https://www.noblego.de/new-world-by-a-j-fernandez-gobernador/","brand":"A.J. Fernandez","series":"New World","details":{"Fazit":"Eine würdige Vertreterin der Kategorie Zigarre des Jahres 2014: Die New World by A.J. Fernandez Gobernador ist ein mittelstarker bis starker Smoke mit einer harmonischen Aromenpalette, die von Süße bis würzige Schärfe einiges bereithält. Unbedingt probieren!","Genuss":"A.J. Fernandez hat einen Hang zu nicaraguanischem Tabak. Schon die Zigarren seiner \u003ca title=\"Pinolero by AJ Fernandez bei Noblego\" href=\"/pinolero-by-aj-fernandez-zigarren/\"\u003ePinolero-Serie\u003c/a\u003e sind nicaraguanische Puros. Und so auch die New World by A.J. Fernandez Gobernador und ihre Geschwister, deren Tabak aus den besten Anbaugebieten Nicaraguas stammt. Das Deckblatt ist ein ölig-dunkles Maduroblatt, das Umblatt wurde in Jalapa gezogen. Der Blend der Einlage besteht aus Viso aus Ometepe, Ligero aus Condega und Finca Soledad Ligero aus Estelí. Die Boxpressed-Toro mit den Maßen von 165 x 21,8 mm entwickelt sich während des gut 90-minütigen Smokes von einer mittleren Stärke zu einem recht kräftigen Zeitgenossen. Dabei stehen im 1. Drittel zunächst Aromen von dunkler Schokolade und Erde im Vordergrund während sich die Pfeffernote und die typische Maduro-Süße noch im Hintergrund halten. Letztere treten dann im zweiten Drittel dominanter auf und die Schokoladennote ist nur noch hintergründig wahrnehmbar. Im letzten Drittel wird die Pfeffernote zunehmend stärker und auch die allgemeine Stärke der Gobernador entwickelt sich von medium zu stark. Die Asche ist nicht allzu fest, weist aber eine schöne mittelgraue Marmorierung auf. Der Abbrand ist durchweg einwandfrei und auch das Zugverhalten macht bei diesem alles in allem sehr runden Smoke keine Ausnahme.","Hintergrund":"Der Name der Serie „New World“ referiert auf die Entdeckung der Neuen Welt Ende des 15. Jahrhunderts, was sich auch auf dem aufwendig gestalteten Zigarrenring widerspiegelt. Mit ihr einhergehend ist auch der erste Kontakt der europäischen Eroberer mit der Tabakpflanze und ihrer Verwendung. Die New World Serie umfasst vier verschiedene Formate: Navegante (Robusto), Almirante (Belicoso), Gobernador (Toro), Virrey (Gordo)."},"diameter_mm":21.8,"ring":55,"length_mm":165,"length_inch":0,"format":"Toro","maker":"AJ Fernandez","manufactureOrigin":"Nicaragua","construction":"Longfiller","isBoxpressed":true,"wrapperOrigin":["Nicaragua"],"fillerOrigin":["Nicaragua"],"binderOrigin":["Nicaragua"],"aromaProfileManufacturer":["Erdig","Pfeffer","Schokolade","Süß","Zedernholz"],"strength":"Stark","flavourStrength":"Medium-aromatisch","smokingDuration":"45 bis 90 Min","price":9.8}
