{"name":"Casa de Torres Robusto","url":"https://www.noblego.de/casa-de-torres-robusto/","brand":"Casa de Torres","series":"Classic","details":{"Fazit":"Mild würzige Aromen aus Nicaragua verpackt in einer edlen Zigarre. Die Casa de Torres Robusto bietet besonders Einsteigern ein erfreuliches erstes Raucherlebnis, das gerne auch schon zur Mittagszeit genossen werden darf.","Genuss":"Die Casa de Torres Robusto verbindet das Beste aus Nicaragua mit dem sanften Aroma Ecuadors. In der Einlage mit erstklassigem nicaraguanischem Piloto ausgestattet, dient als Umblatt ein Criollo ebenfalls aus Nicaragua. Das feine Connecticut Seed Deckblatt wird in Ecuador kultiviert. Per Hand werden diese Zutaten in den Fabriken in Nicaragua zu einer unnachahmlichen Zigarre gerollt, die mild in der Stärke und aromatisch im Geschmack ist. Auf einer Länge von 12,7 cm entfaltet sie bei einem stattlichen Durchmesser von 22 mm über eine Stunde ihr ausgewogen aromatisches Spektrum, das mit Noten von Nuss, Holz und Röstaromen aufwarten kann. Im Hintergrund schwingt eine leichte Süße mit, die sich auch schon im Kaltgeruch des Longfillers wahrnehmen lässt.","Hintergrund":"Die August Schuster GmbH und Co KG hat sich mit edlen Importzigarren und Shortfillern in Eigenproduktion einen respektablen Ruf in der Welt der Aficionados erobert. Schon seit 1909 steht sie für beste Qualität aus Übersee und Deutschland."},"diameter_mm":22,"ring":55,"length_mm":127,"length_inch":0,"format":"Robusto","manufactureOrigin":"Nicaragua","construction":"Longfiller","isBoxpressed":false,"wrapperOrigin":["Ecuador"],"fillerOrigin":["Nicaragua"],"binderOrigin":["Nicaragua"],"aromaProfileManufacturer":["Holz","Nuss","Röstaromen"],"strength":"Mild","flavourStrength":"Mild-aromatisch","smokingDuration":"45 bis 90 Min","price":6.7}
