{"name":"Villiger Serie Dominicana Robusto","url":"https://www.noblego.de/villiger-serie-dominicana-robusto/","brand":"Villiger","series":"Serie Dominicana","details":{"Fazit":"Die Villiger Serie Dominicana Robusto ist eine mittelstarke Dominikanerin, die mit ihrer guten Verarbeitung und den aromatischen Geschmacksnoten auftrumpfen kann. Mit ihrem spitzen Preis-Leistungs-Verhältnis ist sie auch für den kleinen Geldbeutel erschwinglich, ohne dabei auf Qualität verzichten zu müssen.","Genuss":"Der Chef von Villiger, Heinrich Villiger, höchstpersönlich ist verantwortlich für den Blend der Villiger Serie Dominicana Robusto. Die verarbeiteten Tabake stammen aus vier verschiedenen Ländern. So wird die Einlage in der Dominkanischen Republik und Nicaragua angepflanzt, das Umblatt stammt aus Peru und das Deckblatt aus Ecuador. Der mittelkräftige Shortfiller wird durch ein komplexes Aromenspiel ausgezeichnet, das mit nussigen, holzigen und süßen Noten, die an Honig und Schokolade erinnern, aufwarten kann. Mit 12,7 Zentimetern in der Länge und 19 Millimetern im Durchmesser verspricht die Robusto eine ungefähre Rauchdauer von 45 bis 55 Minuten.","Hintergrund":"Villiger Zigarren gibt es seit 1888. In diesem Jahr eröffnete als Jean Villiger in Pfeffikon im Kanton Luzern die erste Zigarrenmanufaktur in seinem eigenen Wohnhaus. Unternehmergeist und Innovationsdenken bescherten dem Hause Villiger schnell einen respektablen Umsatz."},"diameter_mm":19,"ring":48,"length_mm":127,"length_inch":0,"format":"Robusto","manufactureOrigin":"Dominikanische Republik","construction":"Longfiller","isBoxpressed":false,"wrapperOrigin":["Ecuador"],"fillerOrigin":["Dominikanische Republik","Nicaragua"],"binderOrigin":["Peru"],"aromaProfileManufacturer":["Holz","Honig","Nuss","Schokolade"],"strength":"Medium","flavourStrength":"Mild-aromatisch","smokingDuration":"45 bis 90 Min","price":2.9}
