{"name":"Rocky Patel The Edge Nicaragua Toro","url":"https://www.noblego.de/rocky-patel-the-edge-nicaragua-toro/","brand":"Rocky Patel","series":"The Edge Nicaragua","details":{"Genussverlauf":"Mit der Rocky Patel The Edge Nicaragua Toro hält man eine sehr gut verarbeitete Longfiller-Zigarre in den Händen. In Sachen Preis und Leistung sucht die würzig-süße Kreation von Rocky Patel tatsächlich ihresgleichen, denn ein Toro Format für unter sieben Euro von einer derart bestechenden Qualität findet man nicht gerade häufig vor. Geschmacklich bietet die The Edge Nicaragua ausgeprägte Noten von Schokolade, Kaffee, Erde, Holz und Leder, die von einer subtilen Süße und angenehmen Pfeffertönen abgerundet werden. Bei einer festen Aschebildung brennt sie hervorragend gerade ab und lässt durch einen bestens eingestellten Zug viel Rauchentwicklung zu.","Nice to know":"Rocky Patel führt unter der Bezeichnung „The Edge“ einige verschiedene Blends in seinem Sortiment. Eine weitere Serie erscheint unter dem Namen „The Edge Lite“. Diese richtet sich an Freunde weitaus milderer Zigarren, welche in diesem Falle mit den allseits bekannten Connecticut Shade Deckblättern ausgestattet sind.","Resümee":"Liebhabern von abwechslungsreichen und kräftigen Zigarren gereicht die Rocky Patel The Edge Nicaragua Toro zu einem sehr zufriedenstellenden und vor allem preiswerten Genuss. Greifen Sie daher einfach zu, es lohnt sich!"},"diameter_mm":20.6,"ring":52,"length_mm":152,"length_inch":0,"format":"Toro","maker":"Rocky Patel","manufactureOrigin":"Nicaragua","construction":"Longfiller","isBoxpressed":false,"wrapperOrigin":["Nicaragua"],"fillerOrigin":["Nicaragua"],"binderOrigin":["Nicaragua"],"aromaProfileManufacturer":["Holz","Kaffee","Leder","Pfeffer","Schokolade","Süß"],"strength":"Stark","flavourStrength":"Medium-kräftig","smokingDuration":"45 bis 90 Min","price":8.8}
