{"name":"Oliva Serie G Special G","url":"https://www.noblego.de/oliva-serie-g-special-g/","brand":"Oliva","series":"Serie G","details":{"Fazit":"Die Oliva Serie G Special G ist ein perfekter Genussbegleiter zum Kaffee. Man kann sie natürlich auch ohne Begleitgetränk vorzüglich genießen und sich einfach an ihrem feinen cremigen Geschmack erfreuen.","Genuss":"Dem Blend der Oliva Serie G Special G liegen zwei wesentliche Komponenten zugrunde. Ihr schokoladig braunes Deckblatt stammt aus Kamerun und wurde einem langen Reifungsprozess unterzogen. Einlage und Umblatt bilden auf den Punkt gereifte nicaraguanische Tabake. Die von Hand gerollte Figurado weist bei milder Stärke eine außergewöhnlich deutliche Aromaentfaltung auf, was wiederum auf die ideale Reifung der in ihr enthaltenen Tabake zurückzuführen ist. Ihr cremiger Rauch verströmt neben einem erdigen Grundton, schokoladige, holzige und fruchtige Noten, begleitet von einer natürlichen Süße. Daneben treten im weiteren Rauchverlauf noch Nuancen von Kaffee und Leder auf, die der gesamten Aromakomposition noch mehr Komplexität verleihen. Um diesen abwechslungsreichen Genuss voll auskosten zu können, sollten Sie die kleine Zigarre mit einem Ringmaß von 30 gemächlich und besonnen rauchen. Im Zug ist die Oliva Serie G Special G perfekt eingestellt und lässt sich bei schnurgeradem Abbrand bis zu 45 Minuten lang genießen.","Hintergrund":"Hinter der Marke Oliva steckt ein wahres Familienunternehmen mit unglaublich viel Erfahrung und Leidenschaft für Zigarren. Heutzutage zählt das Unternehmen zu den größten Produzenten Nicaraguas, was sich ebenfalls an dem riesigen Sortiment an verschiedensten Longfiller-Zigarren erkennen lässt, die unter der Marke Oliva auf der ganzen Welt erfolgreich vertrieben werden."},"diameter_mm":11.9,"ring":30,"length_mm":95,"length_inch":0,"format":"Figurado","manufactureOrigin":"Nicaragua","construction":"Longfiller","isBoxpressed":false,"wrapperOrigin":["Kamerun"],"fillerOrigin":["Nicaragua","Piloto"],"binderOrigin":["Nicaragua"],"aromaProfileManufacturer":["Cremig","Fruchtig","Holz","Kaffee","Leder","Schokolade","Süß"],"strength":"Mild","flavourStrength":"Medium-aromatisch","smokingDuration":"20 bis 45 Min","price":6.1}
