{"name":"Inca Roca Robusto","url":"https://www.noblego.de/inca-roca-robusto-zigarren/","brand":"Inca","series":"","details":{"Genussverlauf":"Alle Tabake der Inca Roca Robusto stammen von peruanischen Plantagen. Sie wird aus ganzen Tabaken von Hand gerollt und zeichnet sich somit als echte Longfiller Zigarre aus. Ihr Kaltgeruch erinnert an verschiedene Kräuter und am Fuß der Zigarre lässt sich sogar eine interessante Note von schwarzem Tee ausmachen. Einmal entzündet wartet die Roca mit einem fein-cremigen Rauch auf, der im Rauchverlauf durchaus komplex auftretende Aromen von Holz, Leder, Erde und Kaffee an den Gaumen gelangen lässt. Untermalt von feinen süßen Tönen und einer besonders unaufdringlichen Würze ergibt sich ein wunderbar harmonischer Geschmack. Die Konstruktion der delikaten Peruanerin ist sehr gelungen, was sich an ihrem bestens eingestellten Zug und geraden Abbrandverhalten festmachen lässt.","Nice to know":"Hergestellt werden die Inca Zigarren in der Tabacalera del Oriente. Die kleine Manufaktur befindet sich in der am Fuße der Anden gelegenen Kleinstadt Tarapoto, die als wirtschaftliches Zentrum der Region San Martín gilt.","Resümee":"Eine ausgezeichnete und zudem sehr exotische Kreation aus Peru. Jeder, der seinen Geschmackshorizont um eine weiteres Highlight erweitern möchte, sollte sich die delikate Inca Roca Robusto gönnen. Uns hat sie auf jeden Fall sehr begeistert!"},"diameter_mm":19.8,"ring":50,"length_mm":127,"length_inch":0,"format":"Robusto","manufactureOrigin":"Peru","construction":"Longfiller","isBoxpressed":false,"wrapperOrigin":["Peru"],"fillerOrigin":["Peru"],"binderOrigin":["Peru"],"aromaProfileManufacturer":["Cremig","Erdig","Holz","Kaffee","Kräuter","Leder","Süß"],"flavourStrength":"Mild-aromatisch","smokingDuration":"45 bis 60 Min","price":7,"additionalNotes":"Puro"}
