{"name":"Casa Magna Colorado Gran Toro","url":"https://www.noblego.de/casa-magna-colorado-gran-toro/","brand":"Casa Magna","series":"Colorado","details":{"Fazit":"Die Zigarre kann optisch und geschmacklich überzeugen. Als Teil einer besonders in Amerika beliebten Zigarrenlinie macht sie Lust darauf, auch die anderen Vertreterinnen der noch jungen Marke zu testen.","Genuss":"Auch die Casa Magna Colorado Gran Toro beinhaltet als Deckblatt, Umblatt und Einlage Tabak aus Nicaragua. Das Colorado-Deckblatt gibt nicht nur den Namen, sondern hat einen Einfluss auf ihr Aroma und ihren Geschmack.\u003cbr\u003e\u003c/br\u003e Mit ihren Maßen von 152 mm Länge und 23 mm Durchmesser ist die Casa Magna Gran Toro eine sehr stattliche Vertreterin dieser Linie. Sie bietet somit auch den längsten und intensivsten Rauchgenuss. Diese großformatige Puro-Zigarre hat Charakter und kann sich mit berühmteren Zigarren messen. Sie weist im Rauch erdige Töne auf und liefert auch einen Hauch von Kaffee und Holz."},"diameter_mm":23,"ring":58,"length_mm":152,"length_inch":0,"format":"Toro","maker":"Manuel Quesada, Nestor Plasencia","manufactureOrigin":"Nicaragua","construction":"Longfiller","isBoxpressed":false,"wrapperOrigin":["Nicaragua"],"fillerOrigin":["Nicaragua"],"binderOrigin":["Nicaragua"],"aromaProfileManufacturer":["Erdig","Holz","Kaffee"],"strength":"Stark","flavourStrength":"Medium-kräftig","smokingDuration":"90 Min oder länger","price":8.7}
