{"name":"Quintero Tubulares","url":"https://www.noblego.de/quintero-tubulares/","brand":"Quintero","series":"","details":{"Fazit":"Eine wirklich schöne Zigarre aus dem günstigen Kuba-Segment und eine echte Schnäppchenempfehlung.","Genuss":"Kubanische Zigarren müssen nicht immer teuer sein. Die Quintero Tubulares bietet eine schöne Alternative für all jene, die gerne kubanische Aromen genießen, aber nicht so tief in die Tasche greifen können oder wollen. Es handelt sich hierbei um einen Mediumfiller, d.h. die Einlage wird aus größeren Schnittresten der Longfiller-Blätter hergestellt. Daraus wurde per Hand eine Corona mit den Maßen 133 x 16,7 mm gerollt. Abbrand und Zug sind anständig und auch geschmacklich präsentiert sie sich als stilechte Kubanerin. Im Kaltgeruch mit einem Duft nach Schokolade und erdigen Untertönen, im Rauch dann Aromen von Holz, Erde, Kakao und Leder. Sie startet zunächst mild und wird dann im Rauchverlauf kräftiger.","Hintergrund":"Quintero wird im Gegensatz zu vielen anderen kubanischen Marken nicht in Havanna gefertigt, sondern in Cienfuegos an der Südküste Kubas. Die verarbeiteten Tabake stammen aus der Region Vuelta Abajo und Semi Vuelta."},"diameter_mm":16.7,"ring":42,"length_mm":133,"length_inch":0,"format":"Corona","manufactureOrigin":"Kuba","construction":"Mediumfiller","isBoxpressed":false,"wrapperOrigin":["Kuba"],"fillerOrigin":["Kuba"],"binderOrigin":["Kuba"],"aromaProfileManufacturer":["Erdig","Leder","Pfeffer"],"strength":"Medium","flavourStrength":"Medium-aromatisch","smokingDuration":"20 bis 45 Min","price":4.3}
